bharatml_commons/__init__.py
bharatml_commons/column_utils.py
bharatml_commons/feature_metadata_client.py
bharatml_commons/feature_utils.py
bharatml_commons/http_client.py
bharatml_commons/sdk_template.py
bharatml_commons/proto/__init__.py
bharatml_commons/proto/generate_proto.py
bharatml_commons/proto/persist.proto
bharatml_commons/proto/retrieve.proto
bharatml_commons/proto/persist/__init__.py
bharatml_commons/proto/persist/persist_pb2.py
bharatml_commons/proto/persist/persist_pb2_grpc.py
bharatml_commons/proto/retrieve/__init__.py
bharatml_commons/proto/retrieve/retrieve_pb2.py
bharatml_commons/proto/retrieve/retrieve_pb2_grpc.py
bharatml_commons-1.0.1.dist-info/METADATA
bharatml_commons-1.0.1.dist-info/WHEEL
bharatml_commons-1.0.1.dist-info/RECORD
