Metadata-Version: 2.4
Name: bharatml_commons
Version: 1.0.1
Summary: Common utilities and protobuf definitions for BharatML Stack
Project-URL: Homepage, https://github.com/Meesho/BharatMLStack
Project-URL: Bug Tracker, https://github.com/Meesho/BharatMLStack/issues
Project-URL: Source, https://github.com/Meesho/BharatMLStack/tree/main/py-sdk/bharatml_commons
Author-email: Jaya Kommuru <jaya.kommuru@meesho.com>, BharatML Stack Team <bharatml@meesho.com>
License: BharatMLStack Business Source License 1.1
Classifier: License :: Other/Proprietary License
Classifier: Operating System :: OS Independent
Classifier: Programming Language :: Python :: 3
Requires-Python: >=3.7
Requires-Dist: protobuf>=4.24.1
Requires-Dist: requests>=2.25.0
Provides-Extra: dev
Requires-Dist: black; extra == 'dev'
Requires-Dist: flake8; extra == 'dev'
Requires-Dist: isort; extra == 'dev'
Requires-Dist: mypy; extra == 'dev'
Requires-Dist: pytest>=6.0; extra == 'dev'
